gridfia/__init__.py
gridfia/api.py
gridfia/config.py
gridfia/config_templates.py
gridfia/console.py
gridfia/exceptions.py
gridfia/conus/__init__.py
gridfia/conus/cloud_storage.py
gridfia/conus/tile_downloader.py
gridfia/conus/tile_index.py
gridfia/conus/tile_processor.py
gridfia/core/__init__.py
gridfia/core/reproducibility.py
gridfia/core/analysis/__init__.py
gridfia/core/analysis/species_presence.py
gridfia/core/analysis/statistical_analysis.py
gridfia/core/calculations/__init__.py
gridfia/core/calculations/base.py
gridfia/core/calculations/biomass.py
gridfia/core/calculations/diversity.py
gridfia/core/calculations/registry.py
gridfia/core/calculations/species.py
gridfia/core/processors/__init__.py
gridfia/core/processors/forest_metrics.py
gridfia/examples/__init__.py
gridfia/examples/utils.py
gridfia/external/__init__.py
gridfia/external/fia_client.py
gridfia/utils/__init__.py
gridfia/utils/location_config.py
gridfia/utils/montana_config.py
gridfia/utils/parallel_processing.py
gridfia/utils/polygon_utils.py
gridfia/utils/zarr_utils.py
gridfia/visualization/__init__.py
gridfia/visualization/boundaries.py
gridfia/visualization/mapper.py
gridfia/visualization/plots.py
gridfia-0.5.1.dist-info/METADATA
gridfia-0.5.1.dist-info/WHEEL
gridfia-0.5.1.dist-info/licenses/LICENSE
gridfia-0.5.1.dist-info/RECORD
