Metadata-Version: 2.4
Name: gridfia
Version: 0.5.1
Summary: Spatial raster analysis for USDA Forest Service BIGMAP data - Part of the FIA Python Ecosystem
Project-URL: Homepage, https://fiatools.org/tools/gridfia/
Project-URL: Documentation, https://mihiarc.github.io/gridfia/
Project-URL: Repository, https://github.com/mihiarc/gridfia.git
Project-URL: Bug Tracker, https://github.com/mihiarc/gridfia/issues
Project-URL: Changelog, https://github.com/mihiarc/gridfia/releases
Project-URL: Source Code, https://github.com/mihiarc/gridfia
Project-URL: FIA Ecosystem, https://fiatools.org
Author-email: Christopher Mihiar <christopher.mihiar@usda.gov>
Maintainer-email: Christopher Mihiar <christopher.mihiar@usda.gov>
License: MIT
License-File: LICENSE
Keywords: bigmap,biodiversity,biomass,carbon-accounting,cloud-optimized,ecological-modeling,fia,forest-analysis,forest-inventory,forestry,geospatial,gis,landsat,raster,remote-sensing,shannon-diversity,simpson-diversity,species-diversity,species-richness,tree-species,usda,zarr
Classifier: Development Status :: 4 - Beta
Classifier: Environment :: Console
Classifier: Framework :: Pydantic :: 2
Classifier: Intended Audience :: Developers
Classifier: Intended Audience :: Science/Research
Classifier: License :: OSI Approved :: MIT License
Classifier: Natural Language :: English
Classifier: Operating System :: OS Independent
Classifier: Programming Language :: Python :: 3
Classifier: Programming Language :: Python :: 3.9
Classifier: Programming Language :: Python :: 3.10
Classifier: Programming Language :: Python :: 3.11
Classifier: Programming Language :: Python :: 3.12
Classifier: Topic :: Scientific/Engineering :: Atmospheric Science
Classifier: Topic :: Scientific/Engineering :: Bio-Informatics
Classifier: Topic :: Scientific/Engineering :: GIS
Classifier: Topic :: Scientific/Engineering :: Information Analysis
Requires-Python: >=3.9
Requires-Dist: aiohttp>=3.8.0
Requires-Dist: certifi>=2023.0.0
Requires-Dist: contextily>=1.4.0
Requires-Dist: fsspec>=2023.1.0
Requires-Dist: geopandas>=0.10.0
Requires-Dist: matplotlib-scalebar>=0.8.0
Requires-Dist: matplotlib>=3.4.0
Requires-Dist: numcodecs>=0.9.0
Requires-Dist: numpy>=1.21.0
Requires-Dist: pandas>=1.3.0
Requires-Dist: psutil>=5.9.0
Requires-Dist: pydantic-settings>=2.0.0
Requires-Dist: pydantic>=2.0.0
Requires-Dist: pyyaml>=6.0.2
Requires-Dist: rasterio>=1.2.0
Requires-Dist: requests>=2.28.0
Requires-Dist: rich>=13.0.0
Requires-Dist: scikit-learn>=1.6.1
Requires-Dist: shapely>=2.0.0
Requires-Dist: tqdm>=4.67.1
Requires-Dist: xarray>=0.19.0
Requires-Dist: zarr>=2.10.0
Provides-Extra: dev
Requires-Dist: black>=22.0.0; extra == 'dev'
Requires-Dist: flake8>=5.0.0; extra == 'dev'
Requires-Dist: isort>=5.10.0; extra == 'dev'
Requires-Dist: mypy>=1.0.0; extra == 'dev'
Requires-Dist: pre-commit>=2.20.0; extra == 'dev'
Requires-Dist: pytest-cov>=4.0.0; extra == 'dev'
Requires-Dist: pytest>=7.0.0; extra == 'dev'
Provides-Extra: docs
Requires-Dist: mkdocs-material>=9.0.0; extra == 'docs'
Requires-Dist: mkdocs-mermaid2-plugin>=1.0.0; extra == 'docs'
Requires-Dist: mkdocs>=1.5.0; extra == 'docs'
Requires-Dist: mkdocstrings-python>=1.0.0; extra == 'docs'
Requires-Dist: mkdocstrings>=0.24.0; extra == 'docs'
Provides-Extra: test
Requires-Dist: pytest-cov>=4.0.0; extra == 'test'
Requires-Dist: pytest-mock>=3.8.0; extra == 'test'
Requires-Dist: pytest>=7.0.0; extra == 'test'
